{
    "ContactPlan": [
        {
            "SourceID": 1001,
            "DestinationID": 9003,
            "StartTime": 725803264.184,
            "EndTime": 725803764.184,
            "Duration": 500.0,
            "Color": []
        },
        {
            "SourceID": 9003,
            "DestinationID": 1001,
            "StartTime": 725803264.184,
            "EndTime": 725803764.184,
            "Duration": 500.0,
            "Color": []
        },
        {
            "SourceID": 1001,
            "DestinationID": 9003,
            "StartTime": 725803764.184,
            "EndTime": 725804764.184,
            "Duration": 1000.0,
            "Color": []
        },
        {
            "SourceID": 9003,
            "DestinationID": 1001,
            "StartTime": 725803764.184,
            "EndTime": 725804764.184,
            "Duration": 1000.0,
            "Color": []
        },
        {
            "SourceID": 1001,
            "DestinationID": 9003,
            "StartTime": 725804764.184,
            "EndTime": 725804864.184,
            "Duration": 100.0,
            "Color": []
        },
        {
            "SourceID": 9003,
            "DestinationID": 1001,
            "StartTime": 725804764.184,
            "EndTime": 725804864.184,
            "Duration": 100.0,
            "Color": []
        },
        {
            "SourceID": 1001,
            "DestinationID": 9003,
            "StartTime": 725804864.184,
            "EndTime": 725805664.184,
            "Duration": 800.0,
            "Color": []
        },
        {
            "SourceID": 9003,
            "DestinationID": 1001,
            "StartTime": 725804864.184,
            "EndTime": 725805664.184,
            "Duration": 800.0,
            "Color": []
        },
        {
            "SourceID": 2013,
            "DestinationID": 9001,
            "StartTime": 725803264.184,
            "EndTime": 725818564.184,
            "Duration": 15300.0,
            "Color": []
        },
        {
            "SourceID": 9001,
            "DestinationID": 2013,
            "StartTime": 725803264.184,
            "EndTime": 725818564.184,
            "Duration": 15300.0,
            "Color": []
        },
        {
            "SourceID": 1001,
            "DestinationID": 2005,
            "StartTime": 725805664.184,
            "EndTime": 725820964.184,
            "Duration": 15300.0,
            "Color": []
        },
        {
            "SourceID": 1001,
            "DestinationID": 2009,
            "StartTime": 725805664.184,
            "EndTime": 725820964.184,
            "Duration": 15300.0,
            "Color": []
        },
        {
            "SourceID": 2005,
            "DestinationID": 1001,
            "StartTime": 725805664.184,
            "EndTime": 725820964.184,
            "Duration": 15300.0,
            "Color": []
        },
        {
            "SourceID": 2009,
            "DestinationID": 1001,
            "StartTime": 725805664.184,
            "EndTime": 725820964.184,
            "Duration": 15300.0,
            "Color": []
        },
        {
            "SourceID": 1001,
            "DestinationID": 2008,
            "StartTime": 725820964.184,
            "EndTime": 725826464.184,
            "Duration": 5500.0,
            "Color": []
        },
        {
            "SourceID": 1001,
            "DestinationID": 2012,
            "StartTime": 725820964.184,
            "EndTime": 725826464.184,
            "Duration": 5500.0,
            "Color": []
        },
        {
            "SourceID": 2008,
            "DestinationID": 1001,
            "StartTime": 725820964.184,
            "EndTime": 725826464.184,
            "Duration": 5500.0,
            "Color": []
        },
        {
            "SourceID": 2012,
            "DestinationID": 1001,
            "StartTime": 725820964.184,
            "EndTime": 725826464.184,
            "Duration": 5500.0,
            "Color": []
        },
        {
            "SourceID": 1001,
            "DestinationID": 9003,
            "StartTime": 725826464.184,
            "EndTime": 725826764.184,
            "Duration": 300.0,
            "Color": []
        },
        {
            "SourceID": 9003,
            "DestinationID": 1001,
            "StartTime": 725826464.184,
            "EndTime": 725826764.184,
            "Duration": 300.0,
            "Color": []
        },
        {
            "SourceID": 1001,
            "DestinationID": 9001,
            "StartTime": 725826464.184,
            "EndTime": 725826864.184,
            "Duration": 400.0,
            "Color": []
        },
        {
            "SourceID": 9001,
            "DestinationID": 1001,
            "StartTime": 725826464.184,
            "EndTime": 725826864.184,
            "Duration": 400.0,
            "Color": []
        },
        {
            "SourceID": 1001,
            "DestinationID": 9003,
            "StartTime": 725826864.184,
            "EndTime": 725827364.184,
            "Duration": 500.0,
            "Color": []
        },
        {
            "SourceID": 1001,
            "DestinationID": 9001,
            "StartTime": 725826864.184,
            "EndTime": 725827364.184,
            "Duration": 500.0,
            "Color": []
        },
        {
            "SourceID": 9001,
            "DestinationID": 1001,
            "StartTime": 725826864.184,
            "EndTime": 725827364.184,
            "Duration": 500.0,
            "Color": []
        },
        {
            "SourceID": 9003,
            "DestinationID": 1001,
            "StartTime": 725826864.184,
            "EndTime": 725827364.184,
            "Duration": 500.0,
            "Color": []
        },
        {
            "SourceID": 1001,
            "DestinationID": 9001,
            "StartTime": 725827864.184,
            "EndTime": 725828464.184,
            "Duration": 600.0,
            "Color": []
        },
        {
            "SourceID": 9001,
            "DestinationID": 1001,
            "StartTime": 725827864.184,
            "EndTime": 725828464.184,
            "Duration": 600.0,
            "Color": []
        },
        {
            "SourceID": 1001,
            "DestinationID": 9001,
            "StartTime": 725828764.184,
            "EndTime": 725828864.184,
            "Duration": 100.0,
            "Color": []
        },
        {
            "SourceID": 9001,
            "DestinationID": 1001,
            "StartTime": 725828764.184,
            "EndTime": 725828864.184,
            "Duration": 100.0,
            "Color": []
        },
        {
            "SourceID": 1001,
            "DestinationID": 9001,
            "StartTime": 725828864.184,
            "EndTime": 725829264.184,
            "Duration": 400.0,
            "Color": []
        },
        {
            "SourceID": 9001,
            "DestinationID": 1001,
            "StartTime": 725828864.184,
            "EndTime": 725829264.184,
            "Duration": 400.0,
            "Color": []
        },
        {
            "SourceID": 2003,
            "DestinationID": 9002,
            "StartTime": 725803264.184,
            "EndTime": 725837764.184,
            "Duration": 34500.0,
            "Color": []
        },
        {
            "SourceID": 9002,
            "DestinationID": 2003,
            "StartTime": 725803264.184,
            "EndTime": 725837764.184,
            "Duration": 34500.0,
            "Color": []
        },
        {
            "SourceID": 2008,
            "DestinationID": 9002,
            "StartTime": 725837764.184,
            "EndTime": 725845464.184,
            "Duration": 7700.0,
            "Color": []
        },
        {
            "SourceID": 9002,
            "DestinationID": 2008,
            "StartTime": 725837764.184,
            "EndTime": 725845464.184,
            "Duration": 7700.0,
            "Color": []
        },
        {
            "SourceID": 1001,
            "DestinationID": 2001,
            "StartTime": 725829264.184,
            "EndTime": 725850064.184,
            "Duration": 20800.0,
            "Color": []
        },
        {
            "SourceID": 1001,
            "DestinationID": 2015,
            "StartTime": 725829264.184,
            "EndTime": 725850064.184,
            "Duration": 20800.0,
            "Color": []
        },
        {
            "SourceID": 2001,
            "DestinationID": 1001,
            "StartTime": 725829264.184,
            "EndTime": 725850064.184,
            "Duration": 20800.0,
            "Color": []
        },
        {
            "SourceID": 2015,
            "DestinationID": 1001,
            "StartTime": 725829264.184,
            "EndTime": 725850064.184,
            "Duration": 20800.0,
            "Color": []
        },
        {
            "SourceID": 1001,
            "DestinationID": 9001,
            "StartTime": 725850064.184,
            "EndTime": 725850164.184,
            "Duration": 100.0,
            "Color": []
        },
        {
            "SourceID": 9001,
            "DestinationID": 1001,
            "StartTime": 725850064.184,
            "EndTime": 725850164.184,
            "Duration": 100.0,
            "Color": []
        },
        {
            "SourceID": 1001,
            "DestinationID": 9001,
            "StartTime": 725850164.184,
            "EndTime": 725850864.184,
            "Duration": 700.0,
            "Color": []
        },
        {
            "SourceID": 9001,
            "DestinationID": 1001,
            "StartTime": 725850164.184,
            "EndTime": 725850864.184,
            "Duration": 700.0,
            "Color": []
        },
        {
            "SourceID": 1001,
            "DestinationID": 9001,
            "StartTime": 725851364.184,
            "EndTime": 725852064.184,
            "Duration": 700.0,
            "Color": []
        },
        {
            "SourceID": 9001,
            "DestinationID": 1001,
            "StartTime": 725851364.184,
            "EndTime": 725852064.184,
            "Duration": 700.0,
            "Color": []
        },
        {
            "SourceID": 1001,
            "DestinationID": 9002,
            "StartTime": 725850164.184,
            "EndTime": 725852164.184,
            "Duration": 2000.0,
            "Color": []
        },
        {
            "SourceID": 2014,
            "DestinationID": 9003,
            "StartTime": 725833064.184,
            "EndTime": 725852164.184,
            "Duration": 19100.0,
            "Color": []
        },
        {
            "SourceID": 9002,
            "DestinationID": 1001,
            "StartTime": 725850164.184,
            "EndTime": 725852164.184,
            "Duration": 2000.0,
            "Color": []
        },
        {
            "SourceID": 9003,
            "DestinationID": 2014,
            "StartTime": 725833064.184,
            "EndTime": 725852164.184,
            "Duration": 19100.0,
            "Color": []
        },
        {
            "SourceID": 1001,
            "DestinationID": 9002,
            "StartTime": 725852164.184,
            "EndTime": 725852764.184,
            "Duration": 600.0,
            "Color": []
        },
        {
            "SourceID": 9002,
            "DestinationID": 1001,
            "StartTime": 725852164.184,
            "EndTime": 725852764.184,
            "Duration": 600.0,
            "Color": []
        },
        {
            "SourceID": 1001,
            "DestinationID": 2011,
            "StartTime": 725852764.184,
            "EndTime": 725857864.184,
            "Duration": 5100.0,
            "Color": []
        },
        {
            "SourceID": 2011,
            "DestinationID": 1001,
            "StartTime": 725852764.184,
            "EndTime": 725857864.184,
            "Duration": 5100.0,
            "Color": []
        },
        {
            "SourceID": 1001,
            "DestinationID": 2004,
            "StartTime": 725857864.184,
            "EndTime": 725859164.184,
            "Duration": 1300.0,
            "Color": []
        },
        {
            "SourceID": 2004,
            "DestinationID": 1001,
            "StartTime": 725857864.184,
            "EndTime": 725859164.184,
            "Duration": 1300.0,
            "Color": []
        },
        {
            "SourceID": 1001,
            "DestinationID": 2007,
            "StartTime": 725852764.184,
            "EndTime": 725869164.184,
            "Duration": 16400.0,
            "Color": []
        },
        {
            "SourceID": 1001,
            "DestinationID": 2011,
            "StartTime": 725859164.184,
            "EndTime": 725869164.184,
            "Duration": 10000.0,
            "Color": []
        },
        {
            "SourceID": 2007,
            "DestinationID": 1001,
            "StartTime": 725852764.184,
            "EndTime": 725869164.184,
            "Duration": 16400.0,
            "Color": []
        },
        {
            "SourceID": 2011,
            "DestinationID": 1001,
            "StartTime": 725859164.184,
            "EndTime": 725869164.184,
            "Duration": 10000.0,
            "Color": []
        },
        {
            "SourceID": 2002,
            "DestinationID": 9001,
            "StartTime": 725855164.184,
            "EndTime": 725872364.184,
            "Duration": 17200.0,
            "Color": []
        },
        {
            "SourceID": 2016,
            "DestinationID": 9003,
            "StartTime": 725852164.184,
            "EndTime": 725872364.184,
            "Duration": 20200.0,
            "Color": []
        },
        {
            "SourceID": 9001,
            "DestinationID": 2002,
            "StartTime": 725855164.184,
            "EndTime": 725872364.184,
            "Duration": 17200.0,
            "Color": []
        },
        {
            "SourceID": 9003,
            "DestinationID": 2016,
            "StartTime": 725852164.184,
            "EndTime": 725872364.184,
            "Duration": 20200.0,
            "Color": []
        },
        {
            "SourceID": 1001,
            "DestinationID": 2006,
            "StartTime": 725869164.184,
            "EndTime": 725873564.184,
            "Duration": 4400.0,
            "Color": []
        },
        {
            "SourceID": 1001,
            "DestinationID": 2010,
            "StartTime": 725869164.184,
            "EndTime": 725873564.184,
            "Duration": 4400.0,
            "Color": []
        },
        {
            "SourceID": 2006,
            "DestinationID": 1001,
            "StartTime": 725869164.184,
            "EndTime": 725873564.184,
            "Duration": 4400.0,
            "Color": []
        },
        {
            "SourceID": 2010,
            "DestinationID": 1001,
            "StartTime": 725869164.184,
            "EndTime": 725873564.184,
            "Duration": 4400.0,
            "Color": []
        },
        {
            "SourceID": 1001,
            "DestinationID": 9002,
            "StartTime": 725873564.184,
            "EndTime": 725876264.184,
            "Duration": 2700.0,
            "Color": []
        },
        {
            "SourceID": 9002,
            "DestinationID": 1001,
            "StartTime": 725873564.184,
            "EndTime": 725876264.184,
            "Duration": 2700.0,
            "Color": []
        },
        {
            "SourceID": 2012,
            "DestinationID": 9003,
            "StartTime": 725872364.184,
            "EndTime": 725881464.184,
            "Duration": 9100.0,
            "Color": []
        },
        {
            "SourceID": 9003,
            "DestinationID": 2012,
            "StartTime": 725872364.184,
            "EndTime": 725881464.184,
            "Duration": 9100.0,
            "Color": []
        },
        {
            "SourceID": 2008,
            "DestinationID": 9002,
            "StartTime": 725881864.184,
            "EndTime": 725882764.184,
            "Duration": 900.0,
            "Color": []
        },
        {
            "SourceID": 9002,
            "DestinationID": 2008,
            "StartTime": 725881864.184,
            "EndTime": 725882764.184,
            "Duration": 900.0,
            "Color": []
        },
        {
            "SourceID": 2008,
            "DestinationID": 9002,
            "StartTime": 725882864.184,
            "EndTime": 725883364.184,
            "Duration": 500.0,
            "Color": []
        },
        {
            "SourceID": 9002,
            "DestinationID": 2008,
            "StartTime": 725882864.184,
            "EndTime": 725883364.184,
            "Duration": 500.0,
            "Color": []
        },
        {
            "SourceID": 2009,
            "DestinationID": 9002,
            "StartTime": 725883564.184,
            "EndTime": 725884764.184,
            "Duration": 1200.0,
            "Color": []
        },
        {
            "SourceID": 9002,
            "DestinationID": 2009,
            "StartTime": 725883564.184,
            "EndTime": 725884764.184,
            "Duration": 1200.0,
            "Color": []
        },
        {
            "SourceID": 2005,
            "DestinationID": 9002,
            "StartTime": 725884764.184,
            "EndTime": 725885064.184,
            "Duration": 300.0,
            "Color": []
        },
        {
            "SourceID": 9002,
            "DestinationID": 2005,
            "StartTime": 725884764.184,
            "EndTime": 725885064.184,
            "Duration": 300.0,
            "Color": []
        },
        {
            "SourceID": 2009,
            "DestinationID": 9002,
            "StartTime": 725885264.184,
            "EndTime": 725885464.184,
            "Duration": 200.0,
            "Color": []
        },
        {
            "SourceID": 9002,
            "DestinationID": 2009,
            "StartTime": 725885264.184,
            "EndTime": 725885464.184,
            "Duration": 200.0,
            "Color": []
        },
        {
            "SourceID": 2008,
            "DestinationID": 9002,
            "StartTime": 725885464.184,
            "EndTime": 725886964.184,
            "Duration": 1500.0,
            "Color": []
        },
        {
            "SourceID": 9002,
            "DestinationID": 2008,
            "StartTime": 725885464.184,
            "EndTime": 725886964.184,
            "Duration": 1500.0,
            "Color": []
        },
        {
            "SourceID": 2008,
            "DestinationID": 9002,
            "StartTime": 725887064.184,
            "EndTime": 725888064.184,
            "Duration": 1000.0,
            "Color": []
        },
        {
            "SourceID": 9002,
            "DestinationID": 2008,
            "StartTime": 725887064.184,
            "EndTime": 725888064.184,
            "Duration": 1000.0,
            "Color": []
        },
        {
            "SourceID": 2008,
            "DestinationID": 9002,
            "StartTime": 725888164.184,
            "EndTime": 725889564.184,
            "Duration": 1400.0,
            "Color": []
        },
        {
            "SourceID": 9002,
            "DestinationID": 2008,
            "StartTime": 725888164.184,
            "EndTime": 725889564.184,
            "Duration": 1400.0,
            "Color": []
        },
        {
            "SourceID": 1001,
            "DestinationID": 2006,
            "StartTime": 725876264.184,
            "EndTime": 725889664.184,
            "Duration": 13400.0,
            "Color": []
        },
        {
            "SourceID": 1001,
            "DestinationID": 2010,
            "StartTime": 725876264.184,
            "EndTime": 725889664.184,
            "Duration": 13400.0,
            "Color": []
        },
        {
            "SourceID": 2004,
            "DestinationID": 9001,
            "StartTime": 725872364.184,
            "EndTime": 725889664.184,
            "Duration": 17300.0,
            "Color": []
        },
        {
            "SourceID": 2006,
            "DestinationID": 1001,
            "StartTime": 725876264.184,
            "EndTime": 725889664.184,
            "Duration": 13400.0,
            "Color": []
        },
        {
            "SourceID": 2010,
            "DestinationID": 1001,
            "StartTime": 725876264.184,
            "EndTime": 725889664.184,
            "Duration": 13400.0,
            "Color": []
        },
        {
            "SourceID": 9001,
            "DestinationID": 2004,
            "StartTime": 725872364.184,
            "EndTime": 725889664.184,
            "Duration": 17300.0,
            "Color": []
        }
    ]
}