{
    "Positions": [
        {
            "Time": 725803264.184,
            "PositionX": -470.5161716878809,
            "PositionY": 7263.77694675299,
            "PositionZ": 4.4477805937806915e-13
        },
        {
            "Time": 725803864.184,
            "PositionX": -1903.857902657494,
            "PositionY": 7025.607880211406,
            "PositionZ": 4.30194410128266e-13
        },
        {
            "Time": 725804464.184,
            "PositionX": -3261.338551397093,
            "PositionY": 6507.496588794428,
            "PositionZ": 3.984692433964708e-13
        },
        {
            "Time": 725805064.184,
            "PositionX": -4488.867972159224,
            "PositionY": 5730.087724330504,
            "PositionZ": 3.5086667952174465e-13
        },
        {
            "Time": 725805664.184,
            "PositionX": -5537.534053635511,
            "PositionY": 4724.357903972461,
            "PositionZ": 2.8928348925631866e-13
        },
        {
            "Time": 725806264.184,
            "PositionX": -6365.551668853908,
            "PositionY": 3530.3814172340117,
            "PositionZ": 2.1617351511924644e-13
        },
        {
            "Time": 725806864.184,
            "PositionX": -6939.927645210355,
            "PositionY": 2195.7334262712898,
            "PositionZ": 1.344498956131993e-13
        },
        {
            "Time": 725807464.184,
            "PositionX": -7237.775409523438,
            "PositionY": 773.594287270679,
            "PositionZ": 4.7368988387235757e-14
        },
        {
            "Time": 725808064.184,
            "PositionX": -7247.226926082871,
            "PositionY": -679.3694737471152,
            "PositionZ": -4.159938257314132e-14
        },
        {
            "Time": 725808664.184,
            "PositionX": -6967.905589893301,
            "PositionY": -2105.2630929016177,
            "PositionZ": -1.2891018540425114e-13
        },
        {
            "Time": 725809264.184,
            "PositionX": -6410.941233183653,
            "PositionY": -3447.2704426351083,
            "PositionZ": -2.1108443566841824e-13
        },
        {
            "Time": 725809864.184,
            "PositionX": -5598.526645918396,
            "PositionY": -4651.917926505337,
            "PositionZ": -2.848478199295477e-13
        },
        {
            "Time": 725810464.184,
            "PositionX": -4563.0332828368855,
            "PositionY": -5671.205185824512,
            "PositionZ": -3.47261163906393e-13
        },
        {
            "Time": 725811064.184,
            "PositionX": -3345.7213908597087,
            "PositionY": -6464.517721744119,
            "PositionZ": -3.9583754679826376e-13
        },
        {
            "Time": 725811664.184,
            "PositionX": -1995.0959544165487,
            "PositionY": -7000.2452194670095,
            "PositionZ": -4.286413950633417e-13
        },
        {
            "Time": 725812264.184,
            "PositionX": -564.973966050217,
            "PositionY": -7257.0410924622365,
            "PositionZ": -4.4436560725823446e-13
        },
        {
            "Time": 725812864.184,
            "PositionX": 887.6599631686983,
            "PositionY": -7224.673057639865,
            "PositionZ": -4.423836367462391e-13
        },
        {
            "Time": 725813464.184,
            "PositionX": 2304.924211831727,
            "PositionY": -6904.430851106548,
            "PositionZ": -4.227744570870935e-13
        },
        {
            "Time": 725814064.184,
            "PositionX": 3630.34649869533,
            "PositionY": -6309.074837043111,
            "PositionZ": -3.8631941523829774e-13
        },
        {
            "Time": 725814664.184,
            "PositionX": 4811.114074786379,
            "PositionY": -5462.327558778621,
            "PositionZ": -3.344710980376307e-13
        },
        {
            "Time": 725815264.184,
            "PositionX": 5800.178099926545,
            "PositionY": -4397.928490679731,
            "PositionZ": -2.6929545244949417e-13
        },
        {
            "Time": 725815864.184,
            "PositionX": 6558.128349533325,
            "PositionY": -3158.289655976365,
            "PositionZ": -1.9338946589858253e-13
        },
        {
            "Time": 725816464.184,
            "PositionX": 7054.763554009482,
            "PositionY": -1792.8056774284007,
            "PositionZ": -1.0977768671779466e-13
        },
        {
            "Time": 725817064.184,
            "PositionX": 7270.294797240957,
            "PositionY": -355.88560129773927,
            "PositionZ": -2.1791708124595374e-14
        },
        {
            "Time": 725817664.184,
            "PositionX": 7196.134025842883,
            "PositionY": 1095.2150848606484,
            "PositionZ": 6.706258240262449e-14
        },
        {
            "Time": 725818264.184,
            "PositionX": 6835.236248342124,
            "PositionY": 2502.6758538312315,
            "PositionZ": 1.5324469868488935e-13
        },
        {
            "Time": 725818864.184,
            "PositionX": 6201.981790033802,
            "PositionY": 3810.4150529947674,
            "PositionZ": 2.333206299036467e-13
        },
        {
            "Time": 725819464.184,
            "PositionX": 5321.603294983619,
            "PositionY": 4966.324533376719,
            "PositionZ": 3.0409967216633857e-13
        },
        {
            "Time": 725820064.184,
            "PositionX": 4229.180306064495,
            "PositionY": 5924.345950296642,
            "PositionZ": 3.6276156525361833e-13
        },
        {
            "Time": 725820664.184,
            "PositionX": 2968.2414869901477,
            "PositionY": 6646.306002202315,
            "PositionZ": 4.0696886858754533e-13
        },
        {
            "Time": 725821264.184,
            "PositionX": 1589.0301796125575,
            "PositionY": 7103.437483942579,
            "PositionZ": 4.349600988826804e-13
        },
        {
            "Time": 725821864.184,
            "PositionX": 146.50240909449219,
            "PositionY": 7277.52554403827,
            "PositionZ": 4.4561991816097836e-13
        },
        {
            "Time": 725822464.184,
            "PositionX": -1301.8628935636034,
            "PositionY": 7161.633473332896,
            "PositionZ": 4.385235754891836e-13
        },
        {
            "Time": 725823064.184,
            "PositionX": -2698.354194552256,
            "PositionY": 6760.379104809304,
            "PositionZ": 4.139538315863682e-13
        },
        {
            "Time": 725823664.184,
            "PositionX": -3987.326930478713,
            "PositionY": 6089.750811772121,
            "PositionZ": 3.728896919620862e-13
        },
        {
            "Time": 725824264.184,
            "PositionX": -5117.4207209995375,
            "PositionY": 5176.470434986041,
            "PositionZ": 3.169673974543281e-13
        },
        {
            "Time": 725824864.184,
            "PositionX": -6043.605872341236,
            "PositionY": 4056.928525350494,
            "PositionZ": 2.4841522664700373e-13
        }
    ]
}