{
    "Positions": [
        {
            "Time": 725803264.184,
            "PositionX": 4872.6117304429135,
            "PositionY": -2345.0268332580413,
            "PositionZ": 4872.611730442913
        },
        {
            "Time": 725803864.184,
            "PositionX": 5104.879767081842,
            "PositionY": -929.6483890573232,
            "PositionZ": 5104.879767081841
        },
        {
            "Time": 725804464.184,
            "PositionX": 5133.738871129549,
            "PositionY": 522.7728054394311,
            "PositionZ": 5133.738871129548
        },
        {
            "Time": 725805064.184,
            "PositionX": 4958.039123369049,
            "PositionY": 1954.36360544392,
            "PositionZ": 4958.039123369048
        },
        {
            "Time": 725805664.184,
            "PositionX": 4584.781452229396,
            "PositionY": 3308.0808742512068,
            "PositionZ": 4584.781452229396
        },
        {
            "Time": 725806264.184,
            "PositionX": 4028.838675090642,
            "PositionY": 4529.984421627492,
            "PositionZ": 4028.8386750906416
        },
        {
            "Time": 725806864.184,
            "PositionX": 3312.3628762406083,
            "PositionY": 5571.386304341684,
            "PositionZ": 3312.362876240609
        },
        {
            "Time": 725807464.184,
            "PositionX": 2463.902735529247,
            "PositionY": 6390.790844621891,
            "PositionZ": 2463.9027355292474
        },
        {
            "Time": 725808064.184,
            "PositionX": 1517.2659777583237,
            "PositionY": 6955.548066505913,
            "PositionZ": 1517.265977758324
        },
        {
            "Time": 725808664.184,
            "PositionX": 510.17227152351469,
            "PositionY": 7243.154665388353,
            "PositionZ": 510.1722715235153
        },
        {
            "Time": 725809264.184,
            "PositionX": -517.2497482391811,
            "PositionY": 7242.150674757672,
            "PositionZ": -517.2497482391805
        },
        {
            "Time": 725809864.184,
            "PositionX": -1524.0614454846,
            "PositionY": 6952.576099603282,
            "PositionZ": -1524.0614454845993
        },
        {
            "Time": 725810464.184,
            "PositionX": -2470.145422201028,
            "PositionY": 6385.969322378445,
            "PositionZ": -2470.1454222010266
        },
        {
            "Time": 725811064.184,
            "PositionX": -3317.804036009794,
            "PositionY": 5564.907344895713,
            "PositionZ": -3317.804036009792
        },
        {
            "Time": 725811664.184,
            "PositionX": -4033.2614993941174,
            "PositionY": 4522.106185729193,
            "PositionZ": -4033.261499394117
        },
        {
            "Time": 725812264.184,
            "PositionX": -4588.009709416853,
            "PositionY": 3299.1172777871006,
            "PositionZ": -4588.009709416852
        },
        {
            "Time": 725812864.184,
            "PositionX": -4959.944180372014,
            "PositionY": 1944.6718116915247,
            "PositionZ": -4959.944180372013
        },
        {
            "Time": 725813464.184,
            "PositionX": -5134.244819086673,
            "PositionY": 512.7389934102254,
            "PositionZ": -5134.244819086672
        },
        {
            "Time": 725814064.184,
            "PositionX": -5103.966446001191,
            "PositionY": -939.6244122988415,
            "PositionZ": -5103.96644600119
        },
        {
            "Time": 725814664.184,
            "PositionX": -4870.315532497194,
            "PositionY": -2354.547563298127,
            "PositionZ": -4870.315532497193
        },
        {
            "Time": 725815264.184,
            "PositionX": -4442.602127994705,
            "PositionY": -3675.6514612615047,
            "PositionZ": -4442.6021279947045
        },
        {
            "Time": 725815864.184,
            "PositionX": -3837.8688919771807,
            "PositionY": -4850.29542770208,
            "PositionZ": -3837.86889197718
        },
        {
            "Time": 725816464.184,
            "PositionX": -3080.212012162548,
            "PositionY": -5831.674624004591,
            "PositionZ": -3080.2120121625485
        },
        {
            "Time": 725817064.184,
            "PositionX": -2199.821068836993,
            "PositionY": -6580.6850350249815,
            "PositionZ": -2199.821068836994
        },
        {
            "Time": 725817664.184,
            "PositionX": -1231.7761012880399,
            "PositionY": -7067.481607517014,
            "PositionZ": -1231.77610128804
        },
        {
            "Time": 725818264.184,
            "PositionX": -214.64980879557124,
            "PositionY": -7272.667455560446,
            "PositionZ": -214.64980879557184
        },
        {
            "Time": 725818864.184,
            "PositionX": 811.0294154955195,
            "PositionY": -7188.066748048602,
            "PositionZ": 811.0294154955187
        },
        {
            "Time": 725819464.184,
            "PositionX": 1804.392378493643,
            "PositionY": -6817.050483080502,
            "PositionZ": 1804.3923784936421
        },
        {
            "Time": 725820064.184,
            "PositionX": 2725.8575606083223,
            "PositionY": -6174.40216689429,
            "PositionZ": 2725.857560608321
        },
        {
            "Time": 725820664.184,
            "PositionX": 3538.7082792885367,
            "PositionY": -5285.728750909334,
            "PositionZ": 3538.7082792885353
        },
        {
            "Time": 725821264.184,
            "PositionX": 4210.555701772947,
            "PositionY": -4186.44029750033,
            "PositionZ": 4210.555701772946
        },
        {
            "Time": 725821864.184,
            "PositionX": 4714.62940963569,
            "PositionY": -2920.3390316188397,
            "PositionZ": 4714.629409635689
        },
        {
            "Time": 725822464.184,
            "PositionX": 5030.844092586359,
            "PositionY": -1537.8739974971559,
            "PositionZ": 5030.844092586358
        },
        {
            "Time": 725823064.184,
            "PositionX": 5146.599866885626,
            "PositionY": -94.13086818744182,
            "PositionZ": 5146.5998668856255
        },
        {
            "Time": 725823664.184,
            "PositionX": 5057.284330396004,
            "PositionY": 1353.3629975221313,
            "PositionZ": 5057.2843303960035
        },
        {
            "Time": 725824264.184,
            "PositionX": 4766.45634809332,
            "PositionY": 2746.9307897072663,
            "PositionZ": 4766.45634809332
        },
        {
            "Time": 725824864.184,
            "PositionX": 4285.704245684955,
            "PositionY": 4031.044435011343,
            "PositionZ": 4285.704245684954
        }
    ]
}